{
  "NTProvider": {
    "types": {
      "/FMSInfo": "FMSInfo",
      "/LiveWindow/Climb": "Subsystem",
      "/LiveWindow/Drive": "Subsystem",
      "/LiveWindow/Intake": "Subsystem",
      "/LiveWindow/Shooter": "Subsystem",
      "/LiveWindow/Ungrouped/DigitalInput[0]": "Digital Input",
      "/LiveWindow/Ungrouped/DigitalInput[1]": "Digital Input",
      "/LiveWindow/Ungrouped/MecanumDrive[1]": "MecanumDrive",
      "/LiveWindow/Ungrouped/Scheduler": "Scheduler",
      "/LiveWindow/Ungrouped/VictorSP[1]": "Motor Controller",
      "/SmartDashboard/Auto Chooser": "String Chooser",
      "/SmartDashboard/Change Vision Modes": "Command",
      "/SmartDashboard/Climb Run": "Command",
      "/SmartDashboard/Extend/Retract Intake": "Command",
      "/SmartDashboard/Find Distance": "Command",
      "/SmartDashboard/Find Target": "Command",
      "/SmartDashboard/Intake Run": "Command",
      "/SmartDashboard/Open Gate": "Command",
      "/SmartDashboard/Shooter Adjust": "Command",
      "/SmartDashboard/Shooter Mode": "Command",
      "/SmartDashboard/Shooter Run": "Command"
    }
  }
}
